httpx_s3_client/__init__.py
httpx_s3_client/_xml.py
httpx_s3_client/client.py
httpx_s3_client/credentials.py
httpx_s3_client/py.typed
httpx_s3_client/version.py
httpx_s3_client-0.0.4.dist-info/LICENSE
httpx_s3_client-0.0.4.dist-info/LICENSE.md
httpx_s3_client-0.0.4.dist-info/METADATA
httpx_s3_client-0.0.4.dist-info/WHEEL
httpx_s3_client-0.0.4.dist-info/RECORD
