Metadata-Version: 2.1
Name: httpx-s3-client
Version: 0.0.4
Summary: The simple module for putting and getting object from Amazon S3 compatible endpoints
Home-page: https://github.com/Folld/httpx-s3-client
License: Apache Software License
Author: Vladimir Morugin
Author-email: vamorugin@gmail.com
Requires-Python: >=3.7,<4.0
Classifier: Development Status :: 4 - Beta
Classifier: Intended Audience :: Developers
Classifier: License :: OSI Approved :: Apache Software License
Classifier: License :: Other/Proprietary License
Classifier: Natural Language :: English
Classifier: Operating System :: MacOS
Classifier: Operating System :: Microsoft
Classifier: Operating System :: POSIX
Classifier: Programming Language :: Python
Classifier: Programming Language :: Python :: 3
Classifier: Programming Language :: Python :: 3.7
Classifier: Programming Language :: Python :: 3.8
Classifier: Programming Language :: Python :: 3.9
Classifier: Programming Language :: Python :: 3.10
Classifier: Programming Language :: Python :: 3.11
Classifier: Programming Language :: Python :: Implementation :: CPython
Classifier: Programming Language :: Python :: Implementation :: PyPy
Classifier: Topic :: Internet
Classifier: Topic :: Software Development
Classifier: Topic :: Software Development :: Libraries
Requires-Dist: aiomisc (>=17,<18)
Requires-Dist: aws-request-signer (==1.2.0)
Requires-Dist: cached-property (>=1.5.2,<2.0.0) ; python_version < "3.8"
Requires-Dist: httpx (>=0.24.1,<0.25.0)
Requires-Dist: typing_extensions ; python_version < "3.10"
Project-URL: Source, https://github.com/Folld/httpx-s3-client
Project-URL: Tracker, https://github.com/Folld/httpx-s3-client/issues
